PyZwoCapture/ASICamera2.dll
PyZwoCapture/ASICamera2.lib
PyZwoCapture/CameraCapture.py
PyZwoCapture/__init__.py
PyZwoCapture-1.0.1.dist-info/METADATA
PyZwoCapture-1.0.1.dist-info/WHEEL
PyZwoCapture-1.0.1.dist-info/top_level.txt
PyZwoCapture-1.0.1.dist-info/RECORD
