Metadata-Version: 2.1
Name: PyZwoCapture
Version: 1.0.1
Summary: For ZWO ASI cameras: controls, captures, and runs the IOTAflash module
Author-email: "Robert L Anderson, Jr" <bob.anderson.ok@gmail.com>
License: MIT License
Project-URL: Repository, https://github.com/bob-anderson-ok/PyZwoCapture
Keywords: Zwo,ASI,flash-tag,IOTAflash
